marimushka/__init__.py
marimushka/export.py
marimushka/notebook.py
marimushka/templates/README.md
marimushka/templates/tailwind.html.j2
marimushka-0.2.3.dist-info/METADATA
marimushka-0.2.3.dist-info/WHEEL
marimushka-0.2.3.dist-info/entry_points.txt
marimushka-0.2.3.dist-info/licenses/LICENSE
marimushka-0.2.3.dist-info/RECORD
