Metadata-Version: 2.4
Name: marimushka
Version: 0.2.3
Summary: Export marimo notebooks in style
Project-URL: repository, https://github.com/jebel-quant/marimushka
Author-email: Jebel Quant LLC <contact@jqr.ae>
License-File: LICENSE
Requires-Python: >=3.11
Requires-Dist: jinja2>=3.1.6
Requires-Dist: loguru>=0.7.3
Requires-Dist: rich==14.2.0
Requires-Dist: typer>=0.16.0
